applybn/__init__.py
applybn/anomaly_detection/__init__.py
applybn/anomaly_detection/anomaly_detection_pipeline.py
applybn/anomaly_detection/displays/__init__.py
applybn/anomaly_detection/displays/results_display.py
applybn/anomaly_detection/dynamic_anomaly_detector/__init__.py
applybn/anomaly_detection/dynamic_anomaly_detector/data_formatter.py
applybn/anomaly_detection/dynamic_anomaly_detector/dbnod_modified.jar
applybn/anomaly_detection/dynamic_anomaly_detector/fast_time_series_detector.py
applybn/anomaly_detection/estimators/__init__.py
applybn/anomaly_detection/estimators/tabular_estimator.py
applybn/anomaly_detection/scores/__init__.py
applybn/anomaly_detection/scores/mixed.py
applybn/anomaly_detection/scores/model_based.py
applybn/anomaly_detection/scores/proximity_based.py
applybn/anomaly_detection/scores/score.py
applybn/anomaly_detection/static_anomaly_detector/__init__.py
applybn/anomaly_detection/static_anomaly_detector/tabular_detector.py
applybn/core/__init__.py
applybn/core/bamt_wrappers.py
applybn/core/data_iq.py
applybn/core/estimators/__init__.py
applybn/core/estimators/base_estimator.py
applybn/core/estimators/estimator_factory.py
applybn/core/exceptions/__init__.py
applybn/core/exceptions/estimator_exc.py
applybn/core/exceptions/exceptions.py
applybn/core/logger.py
applybn/core/pipelines.py
applybn/core/progress_bar.py
applybn/core/schema.py
applybn/explainable/__init__.py
applybn/explainable/causal_analysis/__init__.py
applybn/explainable/causal_analysis/concept_causal_effect.py
applybn/explainable/causal_analysis/intervention_causal_effect.py
applybn/explainable/nn_layers_importance/__init__.py
applybn/explainable/nn_layers_importance/cnn_filter_importance.py
applybn/feature_extraction/__init__.py
applybn/feature_extraction/bn_feature_extractor.py
applybn/feature_selection/__init__.py
applybn/feature_selection/bn_nmi_feature_selector.py
applybn/feature_selection/ce_feature_selector.py
applybn/imbalanced/__init__.py
applybn-0.1.4.dist-info/METADATA
applybn-0.1.4.dist-info/WHEEL
applybn-0.1.4.dist-info/licenses/LICENSE
applybn-0.1.4.dist-info/RECORD
