Metadata-Version: 2.4
Name: applybn
Version: 0.1.4
Summary: 
License-File: LICENSE
Author: jrzkaminski
Author-email: jkaminski@niuitmo.ru
Requires-Python: >=3.11,<4.0
Classifier: Programming Language :: Python :: 3
Classifier: Programming Language :: Python :: 3.11
Classifier: Programming Language :: Python :: 3.12
Classifier: Programming Language :: Python :: 3.13
Classifier: Programming Language :: Python :: 3.14
Requires-Dist: bamt (>=1.3.0,<2.0.0)
Requires-Dist: bayesian-optimization (>=2.0.3,<3.0.0)
Requires-Dist: econml (==0.15.1)
Requires-Dist: imbalanced-learn (>=0.13.0,<0.14.0)
Requires-Dist: jpype1 (>=1.5.2,<2.0.0)
Requires-Dist: numpy (>=1.26.4,<2.0.0)
Requires-Dist: opencv-python (==4.11.0.86)
Requires-Dist: pandas (>=2.0.0,<3.0.0)
Requires-Dist: pytest (==7.4.4)
Requires-Dist: pytest-cov (==4.1.0)
Requires-Dist: pytest-mock
Requires-Dist: rich (>=13.0.0,<14.0.0)
Requires-Dist: scikit-learn (>=1.5.0,<2.0.0)
Requires-Dist: scipy (==1.14.1)
Requires-Dist: setuptools (==75.6.0)
Requires-Dist: statsmodels (>=0.14.0,<0.15.0)
Requires-Dist: torch (>=2.7.0,<=2.8.1)
Requires-Dist: torchvision (==0.22.0)
